Model/Therabee.py
Model/__init__.py
therabee-0.1.dist-info/METADATA
therabee-0.1.dist-info/WHEEL
therabee-0.1.dist-info/top_level.txt
therabee-0.1.dist-info/RECORD
